Workbook
Name fn: Financial_Transactions!$A$2:$J$10401

Sheet Budget
A1: year | B1: month | C1: business_unit | D1: budgeted_revenue | E1: budgeted_expense
A2: 2022 | B2: 1 | C2: Retail | D2: 1530660 | E2: 1259760
A3: 2022 | B3: 1 | C3: Enterprise | D3: 1689240 | E3: 1152615
A4: 2022 | B4: 1 | C4: Online | D4: 2069088 | E4: 1776169
A5: 2022 | B5: 2 | C5: Retail | D5: 1836984 | E5: 1201730
A6: 2022 | B6: 2 | C6: Enterprise | D6: 1923012 | E6: 1454263
A7: 2022 | B7: 2 | C7: Online | D7: 1516272 | E7: 1117069
A8: 2022 | B8: 3 | C8: Retail | D8: 1510920 | E8: 1106833
A9: 2022 | B9: 3 | C9: Enterprise | D9: 1576692 | E9: 959653
A10: 2022 | B10: 3 | C10: Online | D10: 2119464 | E10: 1677676
A11: 2022 | B11: 4 | C11: Retail | D11: 1731204 | E11: 1275919
A12: 2022 | B12: 4 | C12: Enterprise | D12: 2042184 | E12: 1592655
A13: 2022 | B13: 4 | C13: Online | D13: 2132844 | E13: 1388082
... A73: 2023 | B73: 12 | C73: Online | D73: 2263008 | E73: 1662605
A75: =COUNTBLANK(A:A) -> 0 | B75: =COUNTBLANK(B:B) -> 0 | C75: =COUNTBLANK(C:C) -> 0 | D75: =COUNTBLANK(D:D) -> 0 | E75: =COUNTBLANK(E:E) -> 0
A76: =COUNTBLANK(A1:A73) -> 0 | B76: =COUNTBLANK(B1:B73) -> 0 | C76: =COUNTBLANK(C1:C73) -> 0 | D76: =COUNTBLANK(D1:D73) -> 0 | E76: =COUNTBLANK(E1:E73) -> 0

Sheet Customers
A1: customer_id | B1: customer_name | C1: segment | D1: join_date | E1: region | F1: status | G1: pk_check
A2: CUST10000 | B2: Johnson, Olson and Smith | C2: Online | D2: 43918 | E2: North | F2: Active | G2: =IF(COUNTIF(Financial_Transactions!$H$2:$H$10400,A2)>0,"Valid","Missing") -> Valid
A3: CUST10001 | B3: Colon-Valdez | C3: Enterprise | D3: 43146 | E3: West | F3: Active | G3: =IF(COUNTIF(Financial_Transactions!$H$2:$H$10400,A3)>0,"Valid","Missing") -> Valid
A4: CUST10002 | B4: Henry, Jones and Farley | C4: Online | D4: 44641 | E4: North | F4: Active | G4: =IF(COUNTIF(Financial_Transactions!$H$2:$H$10400,A4)>0,"Valid","Missing") -> Valid
A5: CUST10003 | B5: Williams-Dalton | C5: Retail | D5: 44277 | E5: West | F5: Active | G5: =IF(COUNTIF(Financial_Transactions!$H$2:$H$10400,A5)>0,"Valid","Missing") -> Valid
A6: CUST10004 | B6: Fisher-Serrano | C6: Enterprise | D6: 43406 | E6: East | F6: Active | G6: =IF(COUNTIF(Financial_Transactions!$H$2:$H$10400,A6)>0,"Valid","Missing") -> Valid
A7: CUST10005 | B7: Jennings Ltd | C7: Online | D7: 43663 | E7: South | F7: Active | G7: =IF(COUNTIF(Financial_Transactions!$H$2:$H$10400,A7)>0,"Valid","Missing") -> Valid
A8: CUST10006 | B8: Tate-Haas | C8: Retail | D8: 45212 | E8: West | F8: Active | G8: =IF(COUNTIF(Financial_Transactions!$H$2:$H$10400,A8)>0,"Valid","Missing") -> Valid
A9: CUST10007 | B9: Brooks, Aguilar and Young | C9: Enterprise | D9: 43234 | E9: North | F9: Active | G9: =IF(COUNTIF(Financial_Transactions!$H$2:$H$10400,A9)>0,"Valid","Missing") -> Valid
A10: CUST10008 | B10: Herrera-Ingram | C10: Retail | D10: 43350 | E10: East | F10: Active | G10: =IF(COUNTIF(Financial_Transactions!$H$2:$H$10400,A10)>0,"Valid","Missing") -> Valid
A11: CUST10009 | B11: Dunn, Graham and Brown | C11: Retail | D11: 44229 | E11: West | F11: Active | G11: =IF(COUNTIF(Financial_Transactions!$H$2:$H$10400,A11)>0,"Valid","Missing") -> Valid
A12: CUST10010 | B12: Moore, Walker and Gutierrez | C12: Retail | D12: 42831 | E12: East | F12: Active | G12: =IF(COUNTIF(Financial_Transactions!$H$2:$H$10400,A12)>0,"Valid","Missing") -> Valid
A13: CUST10011 | B13: Turner-Lawson | C13: Enterprise | D13: 42920 | E13: West | F13: Active | G13: =IF(COUNTIF(Financial_Transactions!$H$2:$H$10400,A13)>0,"Valid","Missing") -> Valid
... A401: CUST10399 | B401: Marshall-Horne | C401: Enterprise | D401: 43563 | E401: East | F401: Inactive | G401: =IF(COUNTIF(Financial_Transactions!$H$2:$H$10400,A401)>0,"Valid","Missing") -> Missing
A404: =COUNTBLANK(A1:A404) -> 0 | B404: =COUNTBLANK(B1:B404) -> 0 | C404: =COUNTBLANK(C1:C404) -> 0 | D404: =COUNTBLANK(D1:D404) -> 0 | E404: =COUNTBLANK(E1:E404) -> 0 | F404: =COUNTBLANK(F1:F404) -> 0

Sheet Financial_Transactions
A1: transaction_id | B1: transaction_date | C1: amount | D1: account_type | E1: category | F1: business_unit | G1: region | H1: customer_id | I1: vendor_id | J1: description
A2: TRX100000 | B2: 45172 | C2: -66631.73 | D2: Expense | E2: Supplies | F2: Online | G2: West | I2: VEND1053 | J2: Begin catch control dark practice.
A3: TRX100001 | B3: 45182 | C3: -54305.58 | D3: Expense | E3: Utilities | F3: Enterprise | G3: East | I3: VEND1059 | J3: Style guy soldier boy energy above.
A4: TRX100002 | B4: 45104 | C4: 146074.92 | D4: Revenue | E4: Subscription | F4: Online | G4: East | H4: CUST10122 | J4: Skill surface drug personal western.
A5: TRX100003 | B5: 45102 | C5: 212157.95 | D5: Revenue | E5: Service | F5: Enterprise | G5: West | H5: CUST10027 | J5: Develop many it I rich floor decide.
A6: TRX100004 | B6: 45245 | C6: -35944.73 | D6: Expense | E6: Rent | F6: Enterprise | G6: North | I6: VEND1046 | J6: Choose thought teach never.
A7: TRX100005 | B7: 44989 | C7: 90953.83 | D7: Revenue | E7: Service | F7: Retail | G7: South | H7: CUST10332 | J7: Dinner present unit lay course.
A8: TRX100006 | B8: 45115 | C8: 73251.21 | D8: Revenue | E8: Service | F8: Online | G8: West | H8: CUST10270 | J8: Data ago arm care hundred represent wonder.
A9: TRX100007 | B9: 44644 | C9: -21064.02 | D9: Expense | E9: Marketing | F9: Online | G9: East | I9: VEND1115 | J9: Sign such remember range ability.
A10: TRX100008 | B10: 44775 | C10: 136347.73 | D10: Revenue | E10: Product | F10: Retail | G10: West | H10: CUST10168 | J10: Poor similar feeling close require probably rather thought.
A11: TRX100009 | B11: 45094 | C11: 159482 | D11: Revenue | E11: Product | F11: Retail | G11: West | H11: CUST10151 | J11: Cause worker statement office able foot. | O11: jan | P11: feb | Q11: mar
A12: TRX100010 | B12: 44749 | C12: 15882.36 | D12: Equity | E12: Equity | F12: Retail | G12: South | J12: Ready enter quite attack resource list commercial. | N12: 2023 | O12: 38.07 | P12: 30.06 | Q12: 33.95
A13: TRX100011 | B13: 44781 | C13: 217487.82 | D13: Revenue | E13: Product | F13: Online | G13: North | H13: CUST10353 | J13: Before green media feeling Mr half trouble. | N13: 2022 | O13: 25.54 | P13: 22.79 | Q13: 25.84
A14: TRX100012 | B14: 45001 | C14: -8913.27 | D14: Expense | E14: Other | F14: Enterprise | G14: East | I14: VEND1067 | J14: Rise discover visit security end buy medical think. | N14: total | O14: =SUM(O12:O13) -> 63.61 | P14: =SUM(P12:P13) -> 52.85 | Q14: =SUM(Q12:Q13) -> 59.79
A15: TRX100013 | B15: 45270 | C15: 139523.96 | D15: Revenue | E15: Service | F15: Retail | G15: North | H15: CUST10243 | J15: Military line exist little education family world. | P15: =(P13-O13)/O13 -> -0.10767424 | Q15: =(Q13-P13)/P13 -> 0.13383063
A16: TRX100014 | B16: 45125 | C16: 165589.04 | D16: Revenue | E16: Service | F16: Online | G16: East | H16: CUST10357 | J16: Artist place loss morning. | P16: =(P14-O14)/O14 -> -0.16915579
A17: TRX100015 | B17: 44952 | C17: 262541.15 | D17: Revenue | E17: Service | F17: Retail | G17: West | H17: CUST10045 | J17: Game evidence support skill pretty.
A18: TRX100016 | B18: 45087 | C18: 152113.39 | D18: Revenue | E18: Service | F18: Online | G18: South | H18: CUST10120 | J18: Bad author generation decade increase.
A19: TRX100017 | B19: 44726 | C19: 107495.7 | D19: Revenue | E19: Service | F19: Online | G19: North | H19: CUST10228 | J19: Left own eat wife tell with.
A20: TRX100018 | B20: 45190 | C20: 83127.62 | D20: Revenue | E20: Subscription | F20: Online | G20: West | H20: CUST10333 | J20: Individual first region.
A21: TRX100019 | B21: 44793 | C21: 145634.47 | D21: Revenue | E21: Service | F21: Enterprise | G21: West | H21: CUST10302 | J21: Rise war shake doctor.
A22: TRX100020 | B22: 45062 | C22: 167566.97 | D22: Revenue | E22: Service | F22: Retail | G22: North | H22: CUST10042 | J22: Before expect allow job one set. | M22: =SUMIF(B:B,B11<0,B:B) -> 0
A23: TRX100021 | B23: 44726 | C23: -2000 | D23: Expense | E23: Rent | F23: Online | G23: West | I23: VEND1022 | J23: Side official leave seem financial.
A24: TRX100022 | B24: 44998 | C24: 203374.65 | D24: Revenue | E24: Service | F24: Online | G24: South | H24: CUST10021 | J24: Must require bit relate Congress local improve organization.
A25: TRX100023 | B25: 45189 | C25: 171433.19 | D25: Revenue | E25: Product | F25: Enterprise | G25: West | H25: CUST10218 | J25: Identify loss across fact government sea upon.
A26: TRX100024 | B26: 44850 | C26: -60198.87 | D26: Expense | E26: Payroll | F26: Enterprise | G26: North | I26: VEND1058 | J26: Big fine cause full reality heart condition another.
A27: TRX100025 | B27: 45097 | C27: -40143.88 | D27: Expense | E27: Rent | F27: Retail | G27: West | I27: VEND1037 | J27: Good owner financial any result summer physical. | L27: Total Expenses | M27: =SUMIF(B11:B10410,"<0") -> -1.677413e+08
A28: TRX100026 | B28: 45208 | C28: -38329 | D28: Expense | E28: Marketing | F28: Enterprise | G28: West | I28: VEND1049 | J28: Sport note decide who modern car knowledge.
A29: TRX100027 | B29: 44901 | C29: 193475.45 | D29: Revenue | E29: Service | F29: Retail | G29: South | H29: CUST10146 | J29: Game step assume late home order morning to.
A30: TRX100028 | B30: 45002 | C30: 139672.98 | D30: Revenue | E30: Subscription | F30: Enterprise | G30: South | H30: CUST10074 | J30: Nature need environment operation country easy across choice. | L30: Total Revenue | M30: =SUMIF(B11:B10409,">0") -> 8.7968171e+08
A31: TRX100029 | B31: 45188 | C31: 198385.78 | D31: Revenue | E31: Subscription | F31: Enterprise | G31: North | H31: CUST10011 | J31: Scientist particularly include true listen happy.
A32: TRX100030 | B32: 44814 | C32: 137108.16 | D32: Revenue | E32: Service | F32: Enterprise | G32: East | H32: CUST10325 | J32: Citizen help never simple course. | L32: Net profit | M32: =M30-ABS(M27) -> 7.1194041e+08
A33: TRX100031 | B33: 44624 | C33: -44326.21 | D33: Expense | E33: Other | F33: Retail | G33: East | I33: VEND1053 | J33: Billion newspaper modern fine career somebody.
A34: TRX100032 | B34: 44970 | C34: 162088.99 | D34: Revenue | E34: Service | F34: Enterprise | G34: North | H34: CUST10203 | J34: Wall campaign might anyone. | L34: Total budget Revenue | M34: =SUM([1]Budget!C11:C82) -> 0
A35: TRX100033 | B35: 44847 | C35: 138103.68 | D35: Revenue | E35: Subscription | F35: Online | G35: North | H35: CUST10151 | J35: Could impact decide key.
A36: TRX100034 | B36: 44695 | C36: -10197.61 | D36: Expense | E36: Utilities | F36: Retail | G36: East | I36: VEND1014 | J36: Imagine must who discover since painting. | L36: Total budget Expenses | M36: =SUM([1]Budget!D11:D82) -> 120041652
A37: TRX100035 | B37: 45145 | C37: -62926.94 | D37: Expense | E37: Marketing | F37: Retail | G37: West | I37: VEND1093 | J37: Training nor arrive.
A38: TRX100036 | B38: 45195 | C38: 144593.87 | D38: Revenue | E38: Service | F38: Enterprise | G38: East | H38: CUST10086 | J38: Field some arrive society everybody guy public.
A39: TRX100037 | B39: 44595 | C39: 38814.58 | D39: Revenue | E39: Product | F39: Retail | G39: North | H39: CUST10013 | J39: Order agreement mind everything.
A40: TRX100038 | B40: 44983 | C40: -36977.97 | D40: Expense | E40: Rent | F40: Online | G40: East | I40: VEND1082 | J40: Watch would miss interview water trouble.
A41: TRX100039 | B41: 44914 | C41: -18304.84 | D41: Expense | E41: Payroll | F41: Enterprise | G41: East | I41: VEND1106 | J41: Save in thing model.
A42: TRX100040 | B42: 45228 | C42: 248459.88 | D42: Revenue | E42: Subscription | F42: Online | G42: East | H42: CUST10022 | J42: Defense argue help someone action throw.
A43: TRX100041 | B43: 44838 | C43: 120099.72 | D43: Revenue | E43: Product | F43: Online | G43: East | H43: CUST10128 | J43: Reduce suddenly against ball medical.
A44: TRX100042 | B44: 44888 | C44: -39571.02 | D44: Expense | E44: Other | F44: Online | G44: South | I44: VEND1063 | J44: Far make skill lose audience art.
A45: TRX100043 | B45: 45033 | C45: 79909.54 | D45: Revenue | E45: Subscription | F45: Retail | G45: East | H45: CUST10251 | J45: Tax north line it fund describe.
A46: TRX100044 | B46: 44977 | C46: -50444.36 | D46: Expense | E46: Other | F46: Enterprise | G46: North | I46: VEND1020 | J46: Follow put campaign lose summer lot if others.
A47: TRX100045 | B47: 44879 | C47: -22716.39 | D47: Expense | E47: Supplies | F47: Retail | G47: East | I47: VEND1062 | J47: Structure have effect.
A48: TRX100046 | B48: 44934 | C48: -14936.32 | D48: Expense | E48: Marketing | F48: Online | G48: East | I48: VEND1025 | J48: Second get its since return.
A49: TRX100047 | B49: 45199 | C49: 141946.92 | D49: Revenue | E49: Service | F49: Retail | G49: West | H49: CUST10342 | J49: Then section each support majority.
A50: TRX100048 | B50: 45265 | C50: -28844.76 | D50: Expense | E50: Supplies | F50: Online | G50: West | I50: VEND1060 | J50: Where keep leader computer father brother a give.
A51: TRX100049 | B51: 44782 | C51: -66244 | D51: Expense | E51: Supplies | F51: Enterprise | G51: North | I51: VEND1089 | J51: Big itself serious.
A52: TRX100050 | B52: 45018 | C52: 15704.88 | D52: Asset | E52: Asset | F52: Enterprise | G52: East | J52: Test fill perform voice.
A53: TRX100051 | B53: 44822 | C53: 209846.71 | D53: Revenue | E53: Subscription | F53: Retail | G53: South | H53: CUST10190 | J53: School common voice itself.
A54: TRX100052 | B54: 44728 | C54: -45798.81 | D54: Expense | E54: Marketing | F54: Enterprise | G54: East | I54: VEND1011 | J54: Majority early special record sit scene price.
A55: TRX100053 | B55: 44687 | C55: -22712.23 | D55: Expense | E55: Payroll | F55: Enterprise | G55: North | I55: VEND1079 | J55: Daughter training suffer miss money.
A56: TRX100054 | B56: 44881 | C56: -51925.51 | D56: Expense | E56: Other | F56: Online | G56: East | I56: VEND1098 | J56: Including measure leave road leg mention.
A57: TRX100055 | B57: 44960 | C57: -42768.16 | D57: Expense | E57: Rent | F57: Online | G57: North | I57: VEND1082 | J57: Technology far reach thought probably cover increase.
A58: TRX100056 | B58: 44655 | C58: -22339.95 | D58: Expense | E58: Marketing | F58: Retail | G58: East | I58: VEND1001 | J58: Play prepare red goal.
A59: TRX100057 | B59: 44995 | C59: -43856.82 | D59: Expense | E59: Utilities | F59: Enterprise | G59: West | I59: VEND1042 | J59: Hard this despite certain they both provide machine.
A60: TRX100058 | B60: 44730 | C60: 86224.06 | D60: Revenue | E60: Product | F60: Retail | G60: East | H60: CUST10151 | J60: Summer everyone his magazine six value week.
A61: TRX100059 | B61: 44818 | C61: 196305.77 | D61: Revenue | E61: Service | F61: Enterprise | G61: West | H61: CUST10016 | J61: Pm like matter price personal for.
A62: TRX100060 | B62: 45271 | C62: 144148.9 | D62: Revenue | E62: Product | F62: Online | G62: South | H62: CUST10049 | J62: True shoulder away.
A63: TRX100061 | B63: 44872 | C63: 161193.89 | D63: Revenue | E63: Product | F63: Online | G63: South | H63: CUST10129 | J63: Page truth although under for water analysis.
A64: TRX100062 | B64: 44808 | C64: 157413.67 | D64: Revenue | E64: Service | F64: Online | G64: West | H64: CUST10183 | J64: Early choice speech follow fund measure.
A65: TRX100063 | B65: 44583 | C65: 113690.25 | D65: Revenue | E65: Subscription | F65: Enterprise | G65: West | H65: CUST10348 | J65: Same whether interesting half Republican.
A66: TRX100064 | B66: 45152 | C66: 194267.47 | D66: Revenue | E66: Subscription | F66: Online | G66: East | H66: CUST10075 | J66: Half toward his.
A67: TRX100065 | B67: 45018 | C67: -53590.9 | D67: Expense | E67: Marketing | F67: Enterprise | G67: South | I67: VEND1107 | J67: Source learn expect show.
A68: TRX100066 | B68: 44844 | C68: -29061.06 | D68: Expense | E68: Other | F68: Retail | G68: North | I68: VEND1019 | J68: House performance sign deep.
A69: TRX100067 | B69: 44904 | C69: -48080.35 | D69: Expense | E69: Rent | F69: Retail | G69: North | I69: VEND1030 | J69: Home now local perform by.
A70: TRX100068 | B70: 44749 | C70: 218024.69 | D70: Revenue | E70: Product | F70: Online | G70: North | H70: CUST10321 | J70: Dog eight perhaps audience past eye.
A71: TRX100069 | B71: 44749 | C71: -38127.82 | D71: Expense | E71: Rent | F71: Enterprise | G71: West | I71: VEND1086 | J71: His another government threat choose water fear.
A72: TRX100070 | B72: 44989 | C72: -31873.97 | D72: Expense | E72: Rent | F72: Retail | G72: North | I72: VEND1086 | J72: Enjoy keep pass write state even bank.
A73: TRX100071 | B73: 45082 | C73: 203084.24 | D73: Revenue | E73: Subscription | F73: Online | G73: West | H73: CUST10116 | J73: Possible talk model why we town decade.
A74: TRX100072 | B74: 45290 | C74: 222948.96 | D74: Revenue | E74: Subscription | F74: Online | G74: North | H74: CUST10063 | J74: Black sit anyone language song show watch better.
A75: TRX100073 | B75: 45270 | C75: 238667.54 | D75: Revenue | E75: Product | F75: Enterprise | G75: South | H75: CUST10137 | J75: Rate reflect building guess well TV.
A76: TRX100074 | B76: 44673 | C76: 132774.78 | D76: Revenue | E76: Subscription | F76: Retail | G76: South | H76: CUST10298 | J76: And stop raise somebody nice.
A77: TRX100075 | B77: 45186 | C77: 188545.69 | D77: Revenue | E77: Subscription | F77: Enterprise | G77: North | H77: CUST10187 | J77: Wonder increase hundred today final debate.
A78: TRX100076 | B78: 45056 | C78: 138240.93 | D78: Revenue | E78: Service | F78: Retail | G78: East | H78: CUST10285 | J78: Pick fast one entire.
A79: TRX100077 | B79: 45149 | C79: -14341.81 | D79: Expense | E79: Payroll | F79: Online | G79: North | I79: VEND1095 | J79: East very manager set act perhaps company ability.
A80: TRX100078 | B80: 44904 | C80: 163678.6 | D80: Revenue | E80: Product | F80: Enterprise | G80: West | H80: CUST10207 | J80: Three specific late economic serious word.
A81: TRX100079 | B81: 44851 | C81: 198317.9 | D81: Revenue | E81: Product | F81: Enterprise | G81: West | H81: CUST10207 | J81: Continue beyond suffer plant student.
A82: TRX100080 | B82: 45153 | C82: 188616.88 | D82: Revenue | E82: Product | F82: Retail | G82: North | H82: CUST10108 | J82: Doctor surface girl friend everybody thousand under.
A83: TRX100081 | B83: 44738 | C83: -25218.03 | D83: Expense | E83: Marketing | F83: Online | G83: East | I83: VEND1089 | J83: Kid item feeling less player.
A84: TRX100082 | B84: 45196 | C84: -15892.26 | D84: Expense | E84: Supplies | F84: Enterprise | G84: South | I84: VEND1025 | J84: Increase mouth your indeed.
A85: TRX100083 | B85: 44807 | C85: 199974.44 | D85: Revenue | E85: Subscription | F85: Enterprise | G85: South | H85: CUST10092 | J85: Letter along six agent staff industry who.
A86: TRX100084 | B86: 44686 | C86: 128923.58 | D86: Revenue | E86: Service | F86: Enterprise | G86: North | H86: CUST10082 | J86: Cell prevent goal view water shake matter effect.
A87: TRX100085 | B87: 44982 | C87: 67222.23 | D87: Revenue | E87: Service | F87: Online | G87: West | H87: CUST10209 | J87: End cover a enough speak figure.
A88: TRX100086 | B88: 44923 | C88: 186952.56 | D88: Revenue | E88: Subscription | F88: Online | G88: West | H88: CUST10089 | J88: Economic behind young American artist main personal.
A89: TRX100087 | B89: 45116 | C89: 164462.06 | D89: Revenue | E89: Service | F89: Retail | G89: East | H89: CUST10042 | J89: Girl reveal order deep chair cut sit.
A90: TRX100088 | B90: 44872 | C90: 18077.56 | D90: Equity | E90: Equity | F90: Enterprise | G90: South | J90: Once fact interest difference section remain.
A91: TRX100089 | B91: 45213 | C91: 72337.28 | D91: Revenue | E91: Service | F91: Online | G91: South | H91: CUST10157 | J91: Able finish they defense yet activity.
A92: TRX100090 | B92: 44760 | C92: -40667.5 | D92: Expense | E92: Rent | F92: Online | G92: South | I92: VEND1090 | J92: Instead age animal popular parent baby.
A93: TRX100091 | B93: 44565 | C93: 177006.22 | D93: Revenue | E93: Product | F93: Retail | G93: West | H93: CUST10212 | J93: Choose per range week.
A94: TRX100092 | B94: 44759 | C94: -33821.98 | D94: Expense | E94: Other | F94: Online | G94: West | I94: VEND1059 | J94: Lay buy bar century.
A95: TRX100093 | B95: 44749 | C95: 113760.1 | D95: Revenue | E95: Service | F95: Enterprise | G95: South | H95: CUST10232 | J95: Congress whose main matter coach loss executive.
A96: TRX100094 | B96: 44618 | C96: 68040.32 | D96: Revenue | E96: Service | F96: Retail | G96: South | H96: CUST10121 | J96: Bar rock democratic positive live easy grow.
A97: TRX100095 | B97: 45132 | C97: 114168.76 | D97: Revenue | E97: Product | F97: Retail | G97: West | H97: CUST10237 | J97: Certainly believe white money.
A98: TRX100096 | B98: 45034 | C98: 104796.05 | D98: Revenue | E98: Product | F98: Online | G98: West | H98: CUST10266 | J98: Support visit else lead call.
A99: TRX100097 | B99: 44637 | C99: -40864.74 | D99: Expense | E99: Other | F99: Retail | G99: East | I99: VEND1072 | J99: But share truth conference seem TV.
A100: TRX100098 | B100: 45167 | C100: -10569.47 | D100: Expense | E100: Supplies | F100: Retail | G100: East | I100: VEND1065 | J100: Officer agree interesting nice risk from medical some.
...

Sheet Headcount
A1: employee_id | B1: employee_name | C1: business_unit | D1: join_date | E1: status | F1: region | G1: cost_to_company
A2: EMP1000 | B2: Daniel Thornton | C2: Enterprise | D2: 44968 | E2: Active | F2: South | G2: 1566441
A3: EMP1001 | B3: Ashley Burch | C3: Retail | D3: 44084 | E3: Active | F3: West | G3: 1533942
A4: EMP1002 | B4: Angel Perry | C4: Online | D4: 44620 | E4: Active | F4: East | G4: 962333
A5: EMP1003 | B5: Kimberly Harmon | C5: Online | D5: 44484 | E5: Active | F5: North | G5: 503403
A6: EMP1004 | B6: Sarah Smith DDS | C6: Enterprise | D6: 44957 | E6: Active | F6: West | G6: 1051271
A7: EMP1005 | B7: Sierra Jordan | C7: Enterprise | D7: 44945 | E7: Active | F7: South | G7: 731473
A8: EMP1006 | B8: Adam Wood | C8: Enterprise | D8: 43768 | E8: Active | F8: West | G8: 596883
A9: EMP1007 | B9: Keith Collins | C9: Online | D9: 44993 | E9: Active | F9: East | G9: 864597
A10: EMP1008 | B10: Mitchell Kelly | C10: Enterprise | D10: 44438 | E10: Active | F10: North | G10: 1736454
A11: EMP1009 | B11: Jacob Mendez | C11: Enterprise | D11: 45166 | E11: Active | F11: North | G11: 1479884
A12: EMP1010 | B12: William Bryant | C12: Enterprise | D12: 44563 | E12: Active | F12: North | G12: 1160373
A13: EMP1011 | B13: Sean Daniels | C13: Retail | D13: 44741 | E13: Active | F13: South | G13: 1603487
... A201: EMP1199 | B201: Mr. Alec Nelson | C201: Enterprise | D201: 44808 | E201: Inactive | F201: South | G201: 728593
A205: =COUNTBLANK(A1:A201) -> 0 | B205: =COUNTBLANK(B1:B201) -> 0 | C205: =COUNTBLANK(C1:C201) -> 0 | D205: =COUNTBLANK(D1:D201) -> 0 | E205: =COUNTBLANK(E1:E201) -> 0 | F205: =COUNTBLANK(F1:F201) -> 0 | G205: =COUNTBLANK(G1:G201) -> 0

Sheet Vendors
A1: vendor_id | B1: vendor_name | C1: category | D1: region | E1: active | F1: Pk_check
A2: VEND1000 | B2: Johnson-Howard | C2: Supplies | D2: East | E2: Y | F2: =IF(COUNTIF(Financial_Transactions!$I$2:$I$10400,A2)>0,"Valid","Missing") -> Valid
A3: VEND1001 | B3: Jensen Ltd | C3: Consulting | D3: South | E3: Y | F3: =IF(COUNTIF(Financial_Transactions!$I$2:$I$10400,A3)>0,"Valid","Missing") -> Valid
A4: VEND1002 | B4: Collins Group | C4: Services | D4: North | E4: Y | F4: =IF(COUNTIF(Financial_Transactions!$I$2:$I$10400,A4)>0,"Valid","Missing") -> Valid
A5: VEND1003 | B5: Smith, Kirby and Torres | C5: Utilities | D5: North | E5: Y | F5: =IF(COUNTIF(Financial_Transactions!$I$2:$I$10400,A5)>0,"Valid","Missing") -> Valid
A6: VEND1004 | B6: Mcgrath, Wheeler and Boyd | C6: Utilities | D6: North | E6: Y | F6: =IF(COUNTIF(Financial_Transactions!$I$2:$I$10400,A6)>0,"Valid","Missing") -> Valid
A7: VEND1005 | B7: Cooper-Larson | C7: Supplies | D7: South | E7: Y | F7: =IF(COUNTIF(Financial_Transactions!$I$2:$I$10400,A7)>0,"Valid","Missing") -> Valid
A8: VEND1006 | B8: Ward-David | C8: Utilities | D8: South | E8: Y | F8: =IF(COUNTIF(Financial_Transactions!$I$2:$I$10400,A8)>0,"Valid","Missing") -> Valid
A9: VEND1007 | B9: Savage Ltd | C9: Utilities | D9: West | E9: Y | F9: =IF(COUNTIF(Financial_Transactions!$I$2:$I$10400,A9)>0,"Valid","Missing") -> Valid
A10: VEND1008 | B10: Medina-Lee | C10: Services | D10: South | E10: Y | F10: =IF(COUNTIF(Financial_Transactions!$I$2:$I$10400,A10)>0,"Valid","Missing") -> Valid
A11: VEND1009 | B11: Griffith and Sons | C11: Services | D11: East | E11: Y | F11: =IF(COUNTIF(Financial_Transactions!$I$2:$I$10400,A11)>0,"Valid","Missing") -> Valid
A12: VEND1010 | B12: Thomas-Santana | C12: Rent | D12: South | E12: Y | F12: =IF(COUNTIF(Financial_Transactions!$I$2:$I$10400,A12)>0,"Valid","Missing") -> Valid
A13: VEND1011 | B13: Robinson-Gibbs | C13: Services | D13: West | E13: Y | F13: =IF(COUNTIF(Financial_Transactions!$I$2:$I$10400,A13)>0,"Valid","Missing") -> Valid
... A121: VEND1119 | B121: Graham-Lopez | C121: Consulting | D121: North | E121: N | F121: =IF(COUNTIF(Financial_Transactions!$I$2:$I$10400,A121)>0,"Valid","Missing") -> Valid
A125: =COUNTBLANK(A1:A121) -> 0 | B125: =COUNTBLANK(B1:B121) -> 0 | C125: =COUNTBLANK(C1:C121) -> 0 | D125: =COUNTBLANK(D1:D121) -> 0 | E125: =COUNTBLANK(E1:E121) -> 0

Sheet Data Quality
B1: FINANCIAL PERFORMANCE ANALYSIS - DATA QUALITY REPORT
A3: Duplicate Check | B3: Used Pivot Tables (ID in Rows, Count in Values, Value Filter > 1).
A4: customer_id | B4: Count of customer_id | D4: transaction_id | E4: Count of transaction_id | G4: vendor_id | H4: Count of vendor_id
A7: Duplicate records | B7: 0 | C7: No duplicates found
A9: Missing Value Check | B9: Used COUNTBLANK() and ISBLANK() functions on critical columns.
B11: Financial_Transactions
B12: Customer_id | C12: 4886 | D12: This are not missing values , the transactions was not happened for specific transaction_id.
B13: Vendor_id | C13: 6275 | D13: This are not missing values , the transactions was not happened for specific transaction_id.
A16: Category Validation | B16: Used UNIQUE() function to verify allowed values.
A17: Bussiness Units - | B17: {=_xlfn.UNIQUE(Financial_Transactions!F2:F10401)} -> Online | C17: Region - | D17: {=_xlfn.UNIQUE(Financial_Transactions!G2:G10401)} -> West
B18: Enterprise | D18: East
B19: Retail | D19: North
D20: South
A21: Outlier Detection | B21: Calculated IQR (Q3 - Q1) and flagged values outside Q1/Q3 ± 1.5*IQR.
A23: Outliers in revenue | B23: 51 (0.92%) | C23: Minimal impact on trends
A25: Outliers in expense | B25: 14 (0.34%) | C25: Minimal impact on trends
